DFF.v
module DFF (
    input wire clk,
    input wire reset,
    input wire d,
    output reg q
);

always @(posedge clk or posedge reset) begin
    if (reset) begin
        q <= 1'b0;          // Initialize q to 0 on reset
    end else begin
        q <= d;             // Otherwise, capture data on rising edge of clock
    end
end
endmodule

DFF_tb.v
// Testbench for D Flip Flop

module DFF_tb;

    // Inputs
    reg clk;
    reg reset;
    reg d;

    // Output
    wire q;

    // Instantiate the D Flip Flop
    DFF uut (
        .clk(clk),
        .reset(reset),
        .d(d),
        .q(q)
    );

    // Clock generation
    always begin
        #5 clk = ~clk;
    end

    // Testbench logic
    initial begin
        // Initialize inputs
        clk = 0;
        reset = 0;
        d = 0;

        // Test Case 1 : Reset the flip-flop
        reset = 1;
        #10;
        reset = 0;

        // Test Case 2: Set D to 1, expect Q to follow D
        d = 1;
        #10;

        // Test Case 3: Set D to 0, expect Q to follow D
        d = 0;
        #10;

        // Test Case 4: Activate reset during operation
        d = 1;
        #5 reset = 1;
        #5 reset = 0;

        // Test Case 5: Another D input change
        d = 1;
        #10;

        $finish;
    end

    // Monitor signals during simulation & dump waveforms for analysis in GTKWave
    initial begin
        $monitor("At time %t, clk=%b, reset%b, d=%b, q=%b", $time, clk, reset, d, q);
        $dumpfile("DFF_tb.vcd");
        $dumpvars(0,DFF_tb);
    end

endmodule

DFF_tb.vcd
$date
	Thu Oct 24 03:23:37 2024
$end
$version
	Icarus Verilog
$end
$timescale
	1s
$end
$scope module DFF_tb $end
$var wire 1 ! q $end
$var reg 1 " clk $end
$var reg 1 # d $end
$var reg 1 $ reset $end
$scope module uut $end
$var wire 1 " clk $end
$var wire 1 # d $end
$var wire 1 $ reset $end
$var reg 1 ! q $end
$upscope $end
$upscope $end
$enddefinitions $end
#0
$dumpvars
1$
0#
0"
0!
$end
#5
1"
#10
0"
1#
0$
#15
1!
1"
#20
0"
0#
#25
0!
1"
#30
0"
1#
#35
1"
1$
#40
0"
0$
#45
1!
1"
